seqflow/__init__.py
seqflow/flow.py
seqflow-0.1.4.dist-info/LICENSE
seqflow-0.1.4.dist-info/METADATA
seqflow-0.1.4.dist-info/WHEEL
seqflow-0.1.4.dist-info/top_level.txt
seqflow-0.1.4.dist-info/RECORD
